plcg/__init__.py
plcg/constants/__init__.py
plcg/constants/values.py
plcg/metrics/__init__.py
plcg/metrics/metrics.py
plcg/sequence_scoring/__init__.py
plcg/sequence_scoring/sequence_difference.py
plcg/sequence_scoring/sequence_to_number_conversions.py
plcg/structure_prediction/__init__.py
plcg/structure_prediction/colabfold/__init__.py
plcg/structure_prediction/colabfold/colabfold.py
plcg/structure_prediction/fasta/__init__.py
plcg/structure_prediction/fasta/fasta.py
plcg/structure_scoring/__init__.py
plcg/structure_scoring/metrics/__init__.py
plcg/structure_scoring/metrics/plddt.py
plcg/structure_scoring/rosetta/__init__.py
plcg/structure_scoring/rosetta/calculate_rosetta_scores.py
plcg/structure_scoring/rosetta/rosetta_scores.py
plcg/structure_scoring/rosetta/score_calculations.py
plcg/structure_scoring/spserver/__init__.py
plcg/structure_scoring/spserver/spserver_scores.py
plcg-1.0.3.dist-info/licenses/LICENSE
plcg-1.0.3.dist-info/METADATA
plcg-1.0.3.dist-info/WHEEL
plcg-1.0.3.dist-info/top_level.txt
plcg-1.0.3.dist-info/RECORD
