Metadata-Version: 2.4
Name: plcg
Version: 1.0.3
Summary: Computational biology and machine learning utilities for the Pardee Lab Computation Group
Author: Spencer Perkins
Author-email: spencer.perkins44sp@gmail.com
Project-URL: Code, https://github.com/Pardee-Lab-Computation-Group/plcg
Project-URL: Bug Tracker, https://github.com/Pardee-Lab-Computation-Group/plcg/issues
Classifier: Programming Language :: Python :: 3
Classifier: License :: OSI Approved :: MIT License
Classifier: Operating System :: OS Independent
Requires-Python: >=3.10
License-File: LICENSE
Requires-Dist: pandas==2.2.0
Requires-Dist: numpy==1.26.3
Requires-Dist: python-Levenshtein==0.23.0
Dynamic: author
Dynamic: author-email
Dynamic: classifier
Dynamic: description
Dynamic: description-content-type
Dynamic: license-file
Dynamic: project-url
Dynamic: requires-dist
Dynamic: requires-python
Dynamic: summary
